dtaidistance/__init__.py
dtaidistance/alignment.py
dtaidistance/compilation.log
dtaidistance/dp.py
dtaidistance/dtaidistancec_dtw.pxd
dtaidistance/dtaidistancec_dtw_omp.pxd
dtaidistance/dtaidistancec_ed.pxd
dtaidistance/dtaidistancec_globals.pxd
dtaidistance/dtw.py
dtaidistance/dtw_barycenter.py
dtaidistance/dtw_cc.c
dtaidistance/dtw_cc.cp310-win_amd64.pyd
dtaidistance/dtw_cc.pxd
dtaidistance/dtw_cc.pyx
dtaidistance/dtw_cc_numpy.cp310-win_amd64.pyd
dtaidistance/dtw_cc_omp.c
dtaidistance/dtw_cc_omp.cp310-win_amd64.pyd
dtaidistance/dtw_cc_omp.pyx
dtaidistance/dtw_ndim.py
dtaidistance/dtw_ndim_visualisation.py
dtaidistance/dtw_visualisation.py
dtaidistance/dtw_weighted.py
dtaidistance/ed.py
dtaidistance/ed_cc.c
dtaidistance/ed_cc.cp310-win_amd64.pyd
dtaidistance/ed_cc.pyx
dtaidistance/exceptions.py
dtaidistance/innerdistance.py
dtaidistance/msm.py
dtaidistance/preprocessing.py
dtaidistance/similarity.py
dtaidistance/util.py
dtaidistance/util_numpy.py
dtaidistance/util_numpy_cc.c
dtaidistance/util_numpy_cc.pyx
dtaidistance/clustering/__init__.py
dtaidistance/clustering/hierarchical.py
dtaidistance/clustering/kmeans.py
dtaidistance/clustering/medoids.py
dtaidistance/clustering/visualization.py
dtaidistance/connectors/__init__.py
dtaidistance/connectors/sktime.py
dtaidistance/lib/DTAIDistanceC/DTAIDistanceC/dd_dtw.c
dtaidistance/lib/DTAIDistanceC/DTAIDistanceC/dd_dtw.h
dtaidistance/lib/DTAIDistanceC/DTAIDistanceC/dd_dtw_openmp.c
dtaidistance/lib/DTAIDistanceC/DTAIDistanceC/dd_dtw_openmp.h
dtaidistance/lib/DTAIDistanceC/DTAIDistanceC/dd_ed.c
dtaidistance/lib/DTAIDistanceC/DTAIDistanceC/dd_ed.h
dtaidistance/lib/DTAIDistanceC/DTAIDistanceC/dd_globals.h
dtaidistance/subsequence/__init__.py
dtaidistance/subsequence/dtw.py
dtaidistance/subsequence/localconcurrences.py
dtaidistance/subsequence/subsequencealignment.py
dtaidistance/subsequence/subsequencesearch.py
dtaidistance/symbolization/__init__.py
dtaidistance/symbolization/alignment.py
dtaidistance-2.3.13.dist-info/METADATA
dtaidistance-2.3.13.dist-info/WHEEL
dtaidistance-2.3.13.dist-info/top_level.txt
dtaidistance-2.3.13.dist-info/RECORD
