Metadata-Version: 2.2
Name: dtaidistance
Version: 2.3.13
Summary: Distance measures for time series (Dynamic Time Warping, fast C implementation)
Author-email: Wannes Meert <wannes.meert@cs.kuleuven.be>
License: Apache-2.0
Project-URL: homepage, https://github.com/wannesm/dtaidistance
Project-URL: repository, https://github.com/wannesm/dtaidistance
Project-URL: documentation, https://http://dtaidistance.readthedocs.io
Keywords: dtw,time series,dynamic time warping,distance
Classifier: Programming Language :: Python :: 3
Classifier: License :: OSI Approved :: Apache Software License
Requires-Python: >=3.8
Requires-Dist: numpy
Provides-Extra: tests
Requires-Dist: pytest; extra == "tests"
Requires-Dist: pytest-benchmark; extra == "tests"
Provides-Extra: viz
Requires-Dist: matplotlib>=3.0.0; extra == "viz"
Provides-Extra: dev
Requires-Dist: pytest; extra == "dev"
Requires-Dist: pytest-benchmark; extra == "dev"
Requires-Dist: matplotlib>=3.0.0; extra == "dev"
Requires-Dist: numpy; extra == "dev"
Requires-Dist: scipy; extra == "dev"
Requires-Dist: sphinx; extra == "dev"
Requires-Dist: sphinx_rtd_theme; extra == "dev"
Provides-Extra: numpy
Requires-Dist: numpy; extra == "numpy"
Requires-Dist: scipy; extra == "numpy"
Requires-Dist: pandas; extra == "numpy"
Provides-Extra: all
Requires-Dist: numpy; extra == "all"
Requires-Dist: scipy; extra == "all"
Requires-Dist: pandas; extra == "all"
